pymaniprob/__init__.py
pymaniprob/docs/__init__.py
pymaniprob/docs/basics.py
pymaniprob/probabilitydistributions/__init__.py
pymaniprob/probabilitydistributions/probabilitydistributions.py
pymaniprob/sphere/__init__.py
pymaniprob/sphere/vonmisesfisher.py
pymaniprob/sphere/watson.py
pymaniprob-0.2.2.dist-info/METADATA
pymaniprob-0.2.2.dist-info/RECORD
pymaniprob-0.2.2.dist-info/WHEEL
pymaniprob-0.2.2.dist-info/top_level.txt
