Metadata-Version: 2.1
Name: pymaniprob
Version: 0.2.2
Summary: UNKNOWN
Home-page: http://github.com/danieljtait/pymaniprob
Author: Daniel Tait
Author-email: tait.djk@gmail.com
License: MIT
Platform: UNKNOWN
Requires-Dist: numpydoc
Requires-Dist: numpy
Requires-Dist: matplotlib
Requires-Dist: scipy
